icddl/__init__.py
icddl/main.py
icddl-0.1.8.dist-info/METADATA
icddl-0.1.8.dist-info/WHEEL
icddl-0.1.8.dist-info/entry_points.txt
icddl-0.1.8.dist-info/top_level.txt
icddl-0.1.8.dist-info/RECORD
