Metadata-Version: 2.1
Name: icddl
Version: 0.1.8
Summary: integrated circuit conference information
Author: ChatEDA
License: MIT
Requires-Dist: tabulate
Requires-Dist: requests
Requires-Dist: termcolor
Requires-Dist: arxiv
Requires-Dist: pyyaml
